{
  "category": [
    {
      "data": [
        {
          "level": 1,
          "name": "Table of Contents"
        },
        {
          "level": 2,
          "name": "Filer"
        }
      ],
      "file": "filer.md",
      "source": "https://github.com/yutkat/my-neovim-pluginlist"
    },
    {
      "data": [
        {
          "level": 1,
          "name": "Awesome Neovim [![Awesome](https://awesome.re/badge-flat.svg)](https://awesome.re)"
        },
        {
          "level": 2,
          "name": "File Explorer"
        }
      ],
      "file": "README.md",
      "source": "https://github.com/rockerBOO/awesome-neovim"
    }
  ],
  "data": {
    "commitCountLastYear": 0,
    "createdAt": "2020-11-20T17:26:43Z",
    "description": "Neovim file explorer",
    "isArchived": false,
    "lastCommit": "2024-05-26T14:54:00Z",
    "nameWithOwner": "tamago324/lir.nvim",
    "primaryLanguage": {
      "color": "#000080",
      "name": "Lua"
    },
    "star": 369,
    "topics": [
      "nvim",
      "lua",
      "neovim",
      "neovim-plugin"
    ]
  },
  "domain": "github.com",
  "name": "lir.nvim",
  "owner": "tamago324",
  "url": "https://github.com/tamago324/lir.nvim"
}