{
  "category": [
    {
      "data": [
        {
          "level": 1,
          "name": "Table of Contents"
        },
        {
          "level": 2,
          "name": "Buffer"
        },
        {
          "level": 3,
          "name": "buffer Sharing"
        }
      ],
      "file": "buffer.md",
      "source": "https://github.com/yutkat/my-neovim-pluginlist"
    }
  ],
  "data": {
    "commitCountLastYear": 2,
    "createdAt": "2023-07-11T17:16:39Z",
    "description": "A plugin for effortless buffer sharing between nvim sessions.",
    "isArchived": false,
    "lastCommit": "2024-08-11T12:54:26Z",
    "nameWithOwner": "tomiis4/BufEx.nvim",
    "primaryLanguage": {
      "color": "#000080",
      "name": "Lua"
    },
    "star": 15,
    "topics": [
    ]
  },
  "domain": "github.com",
  "name": "BufEx.nvim",
  "owner": "tomiis4",
  "url": "https://github.com/tomiis4/BufEx.nvim"
}