{
  "category": [
    {
      "data": [
        {
          "level": 1,
          "name": "Table of Contents"
        },
        {
          "level": 2,
          "name": "Testing"
        }
      ],
      "file": "neovim-lua-development.md",
      "source": "https://github.com/yutkat/my-neovim-pluginlist"
    }
  ],
  "data": {
    "commitCountLastYear": 17,
    "createdAt": "2025-03-01T16:01:53Z",
    "description": "Basic framework for testing Neovim plugins",
    "isArchived": false,
    "lastCommit": "2025-03-10T06:01:46Z",
    "nameWithOwner": "Kafva/tsst.nvim",
    "primaryLanguage": {
      "color": "#000080",
      "name": "Lua"
    },
    "star": 1,
    "topics": [
    ]
  },
  "domain": "github.com",
  "name": "tsst.nvim",
  "owner": "Kafva",
  "url": "https://github.com/Kafva/tsst.nvim"
}