{
  "category": [
    {
      "data": [
        {
          "level": 1,
          "name": "Awesome Neovim [![Awesome](https://awesome.re/badge-flat.svg)](https://awesome.re)"
        },
        {
          "level": 2,
          "name": "Media"
        }
      ],
      "file": "README.md",
      "source": "https://github.com/rockerBOO/awesome-neovim"
    }
  ],
  "domain": "git.sr.ht",
  "error": {
    "reason": "UNSUPPORTED_DOMAIN"
  },
  "name": "nekovim",
  "owner": "~elisoli",
  "url": "https://git.sr.ht/~elisoli/nekovim"
}