{
  "category": [
    {
      "data": [
        {
          "level": 1,
          "name": "Table of Contents"
        },
        {
          "level": 2,
          "name": "Security"
        },
        {
          "level": 3,
          "name": "Scan"
        }
      ],
      "file": "security.md",
      "source": "https://github.com/yutkat/my-neovim-pluginlist"
    }
  ],
  "data": {
    "commitCountLastYear": 6,
    "createdAt": "2025-12-19T17:29:58Z",
    "isArchived": false,
    "lastCommit": "2025-12-19T19:32:01Z",
    "nameWithOwner": "johnsaigle/zizmor.nvim",
    "primaryLanguage": {
      "color": "#000080",
      "name": "Lua"
    },
    "star": 1,
    "topics": [
    ]
  },
  "domain": "github.com",
  "name": "zizmor.nvim",
  "owner": "johnsaigle",
  "url": "https://github.com/johnsaigle/zizmor.nvim"
}