{
  "category": [
    {
      "data": [
        {
          "level": 1,
          "name": "Table of Contents"
        },
        {
          "level": 2,
          "name": "Other Standard Feature Enhancement"
        },
        {
          "level": 3,
          "name": "Undo"
        }
      ],
      "file": "readme.md",
      "source": "https://github.com/yutkat/my-neovim-pluginlist"
    },
    {
      "data": [
        {
          "level": 1,
          "name": "Awesome Neovim [![Awesome](https://cdn.rawgit.com/sindresorhus/awesome/d7305f38d29fed78fa85652e3a63e154dd8e8829/media/badge.svg)](https://github.com/sindresorhus/awesome)"
        },
        {
          "level": 2,
          "name": "Editing Support"
        }
      ],
      "file": "README.md",
      "source": "https://github.com/rockerBOO/awesome-neovim"
    }
  ],
  "data": {
    "commitCountLastYear": 33,
    "createdAt": "2025-10-08T15:18:06Z",
    "description": "Modern undotree plugin for nvim",
    "isArchived": false,
    "lastCommit": "2025-11-14T05:00:53Z",
    "nameWithOwner": "XXiaoA/atone.nvim",
    "primaryLanguage": {
      "color": "#000080",
      "name": "Lua"
    },
    "star": 108,
    "topics": [
      "neovim",
      "neovim-plugin",
      "nvim",
      "nvim-plugin"
    ]
  },
  "domain": "github.com",
  "name": "atone.nvim",
  "owner": "XXiaoA",
  "url": "https://github.com/XXiaoA/atone.nvim"
}