{
  "category": [
    {
      "data": [
        {
          "level": 1,
          "name": "Table of Contents"
        },
        {
          "level": 2,
          "name": "Python"
        },
        {
          "level": 3,
          "name": "pyenv"
        },
        {
          "level": 4,
          "name": "pypi"
        }
      ],
      "file": "python.md",
      "source": "https://github.com/yutkat/my-neovim-pluginlist"
    }
  ],
  "data": {
    "commitCountLastYear": 10,
    "createdAt": "2026-01-07T15:51:27Z",
    "isArchived": false,
    "lastCommit": "2026-01-07T16:41:19Z",
    "nameWithOwner": "flaport/pip.nvim",
    "primaryLanguage": {
      "color": "#000080",
      "name": "Lua"
    },
    "star": 1,
    "topics": [
    ]
  },
  "domain": "github.com",
  "name": "pip.nvim",
  "owner": "flaport",
  "url": "https://github.com/flaport/pip.nvim"
}