{
  "category": [
    {
      "data": [
        {
          "level": 1,
          "name": "Awesome Neovim [![Awesome](https://awesome.re/badge-flat.svg)](https://awesome.re)"
        },
        {
          "level": 2,
          "name": "Colorscheme"
        }
      ],
      "file": "README.md",
      "source": "https://github.com/rockerBOO/awesome-neovim"
    }
  ],
  "data": {
    "commitCountLastYear": 25,
    "createdAt": "2024-12-19T19:45:08Z",
    "description": "✨ Looking for a theme that fits your vibe? Whether you're into dark mode, light mode, or something in between, this NekoNight has got you covered. Written in Lua for snappy performance, it's a buffet of color schemes for every taste and mood. 🍭",
    "isArchived": false,
    "lastCommit": "2025-01-25T01:51:07Z",
    "nameWithOwner": "neko-night/nvim",
    "primaryLanguage": {
      "color": "#000080",
      "name": "Lua"
    },
    "star": 61,
    "topics": [
      "neovim",
      "neovim-colorscheme",
      "tokyo-night",
      "tokyonight",
      "alacritty-theme",
      "kitty-themes",
      "colorscheme",
      "theme",
      "themes",
      "emacs-theme"
    ]
  },
  "domain": "github.com",
  "name": "nvim",
  "owner": "neko-night",
  "url": "https://github.com/neko-night/nvim"
}