{
  "category": [
    [
      {
        "level": 0,
        "name": "fuzzy-finder.md"
      },
      {
        "level": 1,
        "name": "FuzzyFinder"
      },
      {
        "level": 3,
        "name": "Telescope Extensions"
      },
      {
        "level": 4,
        "name": "Grep"
      }
    ]
  ],
  "data": {
    "commitCountLastYear": 0,
    "createdAt": "2020-11-23T16:32:26Z",
    "description": "Incorporating some fzf concepts with plenary jobs and telescope",
    "isArchived": false,
    "lastCommit": "2021-04-16T15:11:19Z",
    "nameWithOwner": "nvim-telescope/telescope-fzf-writer.nvim",
    "primaryLanguage": {
      "color": "#000080",
      "name": "Lua"
    },
    "star": 72,
    "topics": [
    ]
  },
  "domain": "github.com",
  "name": "telescope-fzf-writer.nvim",
  "owner": "nvim-telescope",
  "url": "https://github.com/nvim-telescope/telescope-fzf-writer.nvim"
}