{
  "category": [
    {
      "data": [
        {
          "level": 1,
          "name": "Table of Contents"
        },
        {
          "level": 3,
          "name": "CLI"
        },
        {
          "level": 4,
          "name": "tmux"
        }
      ],
      "file": "cli.md",
      "source": "https://github.com/yutkat/my-neovim-pluginlist"
    }
  ],
  "data": {
    "commitCountLastYear": 3,
    "createdAt": "2024-09-24T17:36:10Z",
    "isArchived": false,
    "lastCommit": "2024-11-22T07:04:44Z",
    "nameWithOwner": "cgimenes/tmux-files.nvim",
    "primaryLanguage": {
      "color": "#000080",
      "name": "Lua"
    },
    "star": 1,
    "topics": [
    ]
  },
  "domain": "github.com",
  "name": "tmux-files.nvim",
  "owner": "cgimenes",
  "url": "https://github.com/cgimenes/tmux-files.nvim"
}