{
  "category": [
    {
      "data": [
        {
          "level": 1,
          "name": "Table of Contents"
        },
        {
          "level": 2,
          "name": "Buffer"
        },
        {
          "level": 3,
          "name": "Buffer Management"
        },
        {
          "level": 4,
          "name": "open"
        },
        {
          "level": 5,
          "name": "recent file"
        }
      ],
      "file": "buffer.md",
      "source": "https://github.com/yutkat/my-neovim-pluginlist"
    },
    {
      "data": [
        {
          "level": 1,
          "name": "Table of Contents"
        },
        {
          "level": 2,
          "name": "Buffer"
        },
        {
          "level": 3,
          "name": "Buffer Management"
        },
        {
          "level": 4,
          "name": "open"
        },
        {
          "level": 5,
          "name": "recent file"
        }
      ],
      "file": "buffer.md",
      "source": "https://github.com/yutkat/my-neovim-pluginlist"
    },
    {
      "data": [
        {
          "level": 1,
          "name": "Awesome Neovim [![Awesome](https://cdn.rawgit.com/sindresorhus/awesome/d7305f38d29fed78fa85652e3a63e154dd8e8829/media/badge.svg)](https://github.com/sindresorhus/awesome)"
        },
        {
          "level": 2,
          "name": "Utility"
        }
      ],
      "file": "README.md",
      "source": "https://github.com/rockerBOO/awesome-neovim"
    }
  ],
  "data": {
    "commitCountLastYear": 48,
    "createdAt": "2025-02-20T01:36:51Z",
    "description": "MRU(Most Recently Used) Files for Neovim",
    "isArchived": false,
    "lastCommit": "2025-12-07T06:48:49Z",
    "nameWithOwner": "wsdjeg/mru.nvim",
    "primaryLanguage": {
      "color": "#000080",
      "name": "Lua"
    },
    "star": 7,
    "topics": [
      "mru",
      "neovim-plugin"
    ]
  },
  "domain": "github.com",
  "name": "mru.nvim",
  "owner": "wsdjeg",
  "url": "https://github.com/wsdjeg/mru.nvim"
}