{
  "category": [
    {
      "data": [
        {
          "level": 1,
          "name": "Table of Contents"
        },
        {
          "level": 2,
          "name": "Emoji"
        },
        {
          "level": 3,
          "name": "Emoji FuzzyFinder"
        }
      ],
      "file": "font_emoji.md",
      "source": "https://github.com/yutkat/my-neovim-pluginlist"
    },
    {
      "data": [
        {
          "level": 1,
          "name": "Awesome Neovim [![Awesome](https://awesome.re/badge-flat.svg)](https://awesome.re)"
        },
        {
          "level": 2,
          "name": "Icon"
        }
      ],
      "file": "README.md",
      "source": "https://github.com/rockerBOO/awesome-neovim"
    }
  ],
  "data": {
    "commitCountLastYear": 69,
    "createdAt": "2023-09-23T04:40:52Z",
    "description": "Find Nerd Glyphs Easily 🤓🔭",
    "isArchived": false,
    "lastCommit": "2026-01-20T21:12:18Z",
    "nameWithOwner": "2KAbhishek/nerdy.nvim",
    "primaryLanguage": {
      "color": "#000080",
      "name": "Lua"
    },
    "star": 374,
    "topics": [
      "glyph",
      "neovim",
      "nerdfont",
      "plugin",
      "telescope",
      "utility"
    ]
  },
  "domain": "github.com",
  "name": "nerdy.nvim",
  "owner": "2KAbhishek",
  "url": "https://github.com/2KAbhishek/nerdy.nvim"
}