{
  "category": [
    {
      "data": [
        {
          "level": 1,
          "name": "Awesome Neovim [![Awesome](https://awesome.re/badge-flat.svg)](https://awesome.re)"
        },
        {
          "level": 2,
          "name": "Colorscheme"
        }
      ],
      "file": "README.md",
      "source": "https://github.com/rockerBOO/awesome-neovim"
    }
  ],
  "data": {
    "commitCountLastYear": 10,
    "createdAt": "2022-12-01T13:29:51Z",
    "description": " An arctic, north-bluish clean and elegant Neovim theme. ",
    "isArchived": false,
    "lastCommit": "2025-10-15T14:27:07Z",
    "nameWithOwner": "gbprod/nord.nvim",
    "primaryLanguage": {
      "color": "#000080",
      "name": "Lua"
    },
    "star": 289,
    "topics": [
      "lua",
      "neovim",
      "neovim-colorscheme",
      "nvim",
      "nvim-colorscheme",
      "theme"
    ]
  },
  "domain": "github.com",
  "name": "nord.nvim",
  "owner": "gbprod",
  "url": "https://github.com/gbprod/nord.nvim"
}