{
  "category": [
    {
      "data": [
        {
          "level": 1,
          "name": "Table of Contents"
        },
        {
          "level": 2,
          "name": "Note Taking"
        },
        {
          "level": 3,
          "name": "Scratch Buffer"
        }
      ],
      "file": "note-taking.md",
      "source": "https://github.com/yutkat/my-neovim-pluginlist"
    }
  ],
  "data": {
    "commitCountLastYear": 57,
    "createdAt": "2026-04-04T11:45:27Z",
    "isArchived": false,
    "lastCommit": "2026-04-14T21:06:50Z",
    "nameWithOwner": "Sou1lah/StickyNotes.nvim",
    "primaryLanguage": {
      "color": "#000080",
      "name": "Lua"
    },
    "star": 7,
    "topics": [
    ]
  },
  "domain": "github.com",
  "name": "StickyNotes.nvim",
  "owner": "Sou1lah",
  "url": "https://github.com/Sou1lah/StickyNotes.nvim"
}