{
  "category": [
    [
      {
        "level": 0,
        "name": "integration-apps.md"
      },
      {
        "level": 1,
        "name": "Table of Contents"
      },
      {
        "level": 2,
        "name": "Integration with other apps"
      },
      {
        "level": 3,
        "name": "Windows"
      },
      {
        "level": 4,
        "name": "Everything"
      }
    ]
  ],
  "data": {
    "commitCountLastYear": 7,
    "createdAt": "2022-08-12T03:34:08Z",
    "description": "Search things by es.exe(everything command line interface) for windows user.",
    "isArchived": false,
    "lastCommit": "2023-04-17T06:25:01Z",
    "nameWithOwner": "Verf/telescope-everything.nvim",
    "primaryLanguage": {
      "color": "#000080",
      "name": "Lua"
    },
    "star": 5,
    "topics": [
    ]
  },
  "domain": "github.com",
  "name": "telescope-everything.nvim",
  "owner": "Verf",
  "url": "https://github.com/Verf/telescope-everything.nvim"
}