{
  "category": [
    [
      {
        "level": 0,
        "name": "integration-apps.md"
      },
      {
        "level": 1,
        "name": "Table of Contents"
      },
      {
        "level": 2,
        "name": "Development environment"
      },
      {
        "level": 3,
        "name": "Shell"
      },
      {
        "level": 4,
        "name": "nushell"
      }
    ]
  ],
  "data": {
    "commitCountLastYear": 37,
    "createdAt": "2023-04-20T05:56:38Z",
    "description": "A null-ls source providing language server features for the nushell language in neovim",
    "isArchived": false,
    "lastCommit": "2023-05-20T03:13:52Z",
    "nameWithOwner": "zioroboco/nu-ls.nvim",
    "primaryLanguage": {
      "color": "#000080",
      "name": "Lua"
    },
    "star": 13,
    "topics": [
      "neovim",
      "nushell"
    ]
  },
  "domain": "github.com",
  "name": "nu-ls.nvim",
  "owner": "zioroboco",
  "url": "https://github.com/zioroboco/nu-ls.nvim"
}