{
  "category": [
    {
      "data": [
      ],
      "file": "Archived.md",
      "source": "https://github.com/yutkat/my-neovim-pluginlist"
    }
  ],
  "data": {
    "commitCountLastYear": 0,
    "createdAt": "2023-09-16T14:19:52Z",
    "description": "Run your npm scripts from the debugger dialog",
    "isArchived": true,
    "lastCommit": "2023-09-22T18:53:05Z",
    "nameWithOwner": "zyriab/npm-dap.nvim",
    "primaryLanguage": {
      "color": "#000080",
      "name": "Lua"
    },
    "star": 4,
    "topics": [
    ]
  },
  "domain": "github.com",
  "name": "npm-dap.nvim",
  "owner": "zyriab",
  "url": "https://github.com/ZyriabDsgn/npm-dap.nvim"
}