{
  "category": [
    {
      "data": [
        {
          "level": 1,
          "name": "Table of Contents"
        },
        {
          "level": 2,
          "name": "Terminal"
        },
        {
          "level": 3,
          "name": "Terminal Enhancement"
        }
      ],
      "file": "terminal.md",
      "source": "https://github.com/yutkat/my-neovim-pluginlist"
    }
  ],
  "data": {
    "commitCountLastYear": 1,
    "createdAt": "2022-07-01T13:01:01Z",
    "description": "Simple terminal toggle in Neovim",
    "isArchived": false,
    "lastCommit": "2025-06-22T07:43:48Z",
    "nameWithOwner": "lukoshkin/bterm.nvim",
    "primaryLanguage": {
      "color": "#000080",
      "name": "Lua"
    },
    "star": 1,
    "topics": [
      "neovim-lua-plugin",
      "vim-terminal"
    ]
  },
  "domain": "github.com",
  "name": "bterm.nvim",
  "owner": "lukoshkin",
  "url": "https://github.com/lukoshkin/bterm.nvim"
}