{
  "category": [
    {
      "data": [
        {
          "level": 1,
          "name": "Language specific"
        },
        {
          "level": 2,
          "name": "Programing Language / Framework"
        },
        {
          "level": 3,
          "name": "Dart, Flutter"
        }
      ],
      "file": "language-specific.md",
      "source": "https://github.com/yutkat/my-neovim-pluginlist"
    }
  ],
  "data": {
    "commitCountLastYear": 26,
    "createdAt": "2023-07-12T08:27:58Z",
    "description": "A Neovim plugin for Bloc support similar to the Bloc Vscode Extension",
    "isArchived": false,
    "lastCommit": "2024-04-02T12:48:07Z",
    "nameWithOwner": "RobertPietraru/bloc.nvim",
    "primaryLanguage": {
      "color": "#000080",
      "name": "Lua"
    },
    "star": 7,
    "topics": [
    ]
  },
  "domain": "github.com",
  "name": "bloc.nvim",
  "owner": "RobertPietraru",
  "url": "https://github.com/RobertPietraru/bloc.nvim"
}