{
  "category": [
    {
      "data": [
        {
          "level": 1,
          "name": "Table of Contents"
        },
        {
          "level": 2,
          "name": "Jump"
        },
        {
          "level": 3,
          "name": "Brackets"
        }
      ],
      "file": "jump.md",
      "source": "https://github.com/yutkat/my-neovim-pluginlist"
    },
    {
      "data": [
        {
          "level": 1,
          "name": "Awesome Neovim [![Awesome](https://cdn.rawgit.com/sindresorhus/awesome/d7305f38d29fed78fa85652e3a63e154dd8e8829/media/badge.svg)](https://github.com/sindresorhus/awesome)"
        },
        {
          "level": 2,
          "name": "Motion"
        }
      ],
      "file": "README.md",
      "source": "https://github.com/rockerBOO/awesome-neovim"
    }
  ],
  "data": {
    "commitCountLastYear": 6,
    "createdAt": "2023-08-11T11:45:48Z",
    "description": "🌲 A Neovim plugin for jumping between significant code elements, such as brackets, quotes, etc.",
    "isArchived": false,
    "lastCommit": "2023-09-29T17:52:28Z",
    "nameWithOwner": "roobert/tabtree.nvim",
    "primaryLanguage": {
      "color": "#000080",
      "name": "Lua"
    },
    "star": 37,
    "topics": [
    ]
  },
  "domain": "github.com",
  "name": "tabtree.nvim",
  "owner": "roobert",
  "url": "https://github.com/roobert/tabtree.nvim"
}