{
  "category": [
    {
      "data": [
        {
          "level": 1,
          "name": "Table of Contents"
        },
        {
          "level": 2,
          "name": "Documentation"
        },
        {
          "level": 3,
          "name": "Markdown"
        },
        {
          "level": 4,
          "name": "Pandoc Preview"
        }
      ],
      "file": "documentation.md",
      "source": "https://github.com/yutkat/my-neovim-pluginlist"
    },
    {
      "data": [
        {
          "level": 1,
          "name": "Awesome Neovim [![Awesome](https://awesome.re/badge-flat.svg)](https://awesome.re)"
        },
        {
          "level": 2,
          "name": "Programming Languages Support"
        },
        {
          "level": 3,
          "name": "Markdown and LaTeX"
        }
      ],
      "file": "README.md",
      "source": "https://github.com/rockerBOO/awesome-neovim"
    }
  ],
  "data": {
    "commitCountLastYear": 0,
    "createdAt": "2018-05-10T17:51:29Z",
    "description": "Markdown preview for neovim using pandoc and live-server",
    "isArchived": false,
    "lastCommit": "2022-05-21T09:13:17Z",
    "nameWithOwner": "davidgranstrom/nvim-markdown-preview",
    "primaryLanguage": {
      "color": "#663399",
      "name": "CSS"
    },
    "star": 111,
    "topics": [
    ]
  },
  "domain": "github.com",
  "name": "nvim-markdown-preview",
  "owner": "davidgranstrom",
  "url": "https://github.com/davidgranstrom/nvim-markdown-preview"
}