{
  "category": [
    {
      "data": [
      ],
      "file": "Archived.md",
      "source": "https://github.com/yutkat/my-neovim-pluginlist"
    }
  ],
  "data": {
    "commitCountLastYear": 4,
    "createdAt": "2022-09-13T15:34:43Z",
    "description": "IDE-Like support for NeoVim",
    "isArchived": true,
    "lastCommit": "2023-03-03T16:19:07Z",
    "nameWithOwner": "Dax89/IDE.nvim",
    "primaryLanguage": {
      "color": "#000080",
      "name": "Lua"
    },
    "star": 54,
    "topics": [
      "neovim",
      "neovim-plugin",
      "nvim",
      "nvim-plugin",
      "lua",
      "nvim-lua"
    ]
  },
  "domain": "github.com",
  "name": "IDE.nvim",
  "owner": "Dax89",
  "url": "https://github.com/Dax89/ide.nvim"
}