{
  "category": [
    {
      "data": [
        {
          "level": 1,
          "name": "Table of Contents"
        },
        {
          "level": 2,
          "name": "Buffer"
        },
        {
          "level": 3,
          "name": "Buffer Management"
        }
      ],
      "file": "buffer_window_tab-management.md",
      "source": "https://github.com/yutkat/my-neovim-pluginlist"
    }
  ],
  "data": {
    "commitCountLastYear": 4,
    "createdAt": "2024-02-12T13:30:46Z",
    "description": "Smooth sailing through buffers of interest in neovim",
    "isArchived": false,
    "lastCommit": "2024-02-19T14:52:08Z",
    "nameWithOwner": "desdic/marlin.nvim",
    "primaryLanguage": {
      "color": "#000080",
      "name": "Lua"
    },
    "star": 6,
    "topics": [
    ]
  },
  "domain": "github.com",
  "name": "marlin.nvim",
  "owner": "desdic",
  "url": "https://github.com/desdic/marlin.nvim"
}