{
  "category": [
    [
      {
        "level": 0,
        "name": "Archived.md"
      },
      {
        "level": 1,
        "name": "Neovim distribution"
      }
    ]
  ],
  "data": {
    "commitCountLastYear": 30,
    "createdAt": "2022-02-24T22:01:39Z",
    "description": "Blazingly fast SHUTTHEFUCKUP. ",
    "isArchived": false,
    "lastCommit": "2023-03-30T07:24:32Z",
    "nameWithOwner": "dharmx/nvim",
    "primaryLanguage": {
      "color": "#000080",
      "name": "Lua"
    },
    "star": 47,
    "topics": [
      "slow",
      "your-mother",
      "nvim-config"
    ]
  },
  "domain": "github.com",
  "name": "nvim",
  "owner": "dharmx",
  "url": "https://github.com/pagankeymaster/KrakeNvim"
}