{
  "category": [
    {
      "data": [
        {
          "level": 1,
          "name": "Table of Contents"
        },
        {
          "level": 2,
          "name": "Motion"
        },
        {
          "level": 3,
          "name": "Vertical Move"
        }
      ],
      "file": "motion.md",
      "source": "https://github.com/yutkat/my-neovim-pluginlist"
    },
    {
      "data": [
        {
          "level": 1,
          "name": "Awesome Neovim [![Awesome](https://awesome.re/badge-flat.svg)](https://awesome.re)"
        },
        {
          "level": 2,
          "name": "Motion"
        },
        {
          "level": 3,
          "name": "Tree-sitter Based"
        }
      ],
      "file": "README.md",
      "source": "https://github.com/rockerBOO/awesome-neovim"
    }
  ],
  "data": {
    "commitCountLastYear": 2,
    "createdAt": "2022-05-20T17:20:01Z",
    "isArchived": false,
    "lastCommit": "2025-12-26T11:00:37Z",
    "nameWithOwner": "drybalka/tree-climber.nvim",
    "primaryLanguage": {
      "color": "#000080",
      "name": "Lua"
    },
    "star": 152,
    "topics": [
    ]
  },
  "domain": "github.com",
  "name": "tree-climber.nvim",
  "owner": "drybalka",
  "url": "https://github.com/drybalka/tree-climber.nvim"
}