{
  "category": [
    {
      "data": [
        {
          "level": 1,
          "name": "Table of Contents"
        },
        {
          "level": 2,
          "name": "Protocol"
        },
        {
          "level": 3,
          "name": "httpyac"
        }
      ],
      "file": "protocol.md",
      "source": "https://github.com/yutkat/my-neovim-pluginlist"
    }
  ],
  "data": {
    "commitCountLastYear": 6,
    "createdAt": "2024-06-21T13:56:22Z",
    "description": "A simple plugin which integrates HttpYac in Neovim",
    "isArchived": false,
    "lastCommit": "2024-09-03T07:14:41Z",
    "nameWithOwner": "abidibo/nvim-httpyac",
    "primaryLanguage": {
      "color": "#000080",
      "name": "Lua"
    },
    "star": 6,
    "topics": [
    ]
  },
  "domain": "github.com",
  "name": "nvim-httpyac",
  "owner": "abidibo",
  "url": "https://github.com/abidibo/nvim-httpyac"
}