{
  "category": [
    {
      "data": [
        {
          "level": 1,
          "name": "Table of Contents"
        },
        {
          "level": 2,
          "name": "AI Completion"
        },
        {
          "level": 3,
          "name": "Copilot"
        }
      ],
      "file": "ai.md",
      "source": "https://github.com/yutkat/my-neovim-pluginlist"
    }
  ],
  "data": {
    "commitCountLastYear": 9,
    "createdAt": "2025-11-26T21:15:12Z",
    "isArchived": false,
    "lastCommit": "2025-11-30T19:15:48Z",
    "nameWithOwner": "agretta/cccontext.nvim",
    "primaryLanguage": {
      "color": "#000080",
      "name": "Lua"
    },
    "star": 1,
    "topics": [
    ]
  },
  "domain": "github.com",
  "name": "cccontext.nvim",
  "owner": "agretta",
  "url": "https://github.com/agretta/cccontext.nvim"
}