{
  "category": [
    {
      "data": [
      ],
      "file": "Archived.md",
      "source": "https://github.com/yutkat/my-neovim-pluginlist"
    }
  ],
  "data": {
    "commitCountLastYear": 3,
    "createdAt": "2025-06-24T12:38:40Z",
    "isArchived": true,
    "lastCommit": "2025-07-05T15:21:15Z",
    "nameWithOwner": "arakkkkk/obsidian-kanban.nvim",
    "primaryLanguage": {
      "color": "#000080",
      "name": "Lua"
    },
    "star": 1,
    "topics": [
    ]
  },
  "domain": "github.com",
  "name": "obsidian-kanban.nvim",
  "owner": "arakkkkk",
  "url": "https://github.com/arakkkkk/obsidian-kanban.nvim"
}