{
  "category": [
    {
      "data": [
        {
          "level": 1,
          "name": "Table of Contents"
        },
        {
          "level": 2,
          "name": "Other Standard Feature Enhancement"
        },
        {
          "level": 3,
          "name": "Shada"
        }
      ],
      "file": "readme.md",
      "source": "https://github.com/yutkat/my-neovim-pluginlist"
    }
  ],
  "data": {
    "commitCountLastYear": 5,
    "createdAt": "2025-07-31T07:46:35Z",
    "isArchived": false,
    "lastCommit": "2025-08-13T08:11:24Z",
    "nameWithOwner": "mart-mihkel/pshada.nvim",
    "primaryLanguage": {
      "color": "#000080",
      "name": "Lua"
    },
    "star": 1,
    "topics": [
      "neovim",
      "neovim-plugin"
    ]
  },
  "domain": "github.com",
  "name": "pshada.nvim",
  "owner": "mart-mihkel",
  "url": "https://github.com/mart-mihkel/pshada.nvim"
}