{
  "category": [
    {
      "data": [
        {
          "level": 1,
          "name": "Table of Contents"
        },
        {
          "level": 2,
          "name": "Toy"
        },
        {
          "level": 3,
          "name": "Training"
        }
      ],
      "file": "toy.md",
      "source": "https://github.com/yutkat/my-neovim-pluginlist"
    }
  ],
  "data": {
    "commitCountLastYear": 20,
    "createdAt": "2026-01-15T17:29:02Z",
    "isArchived": false,
    "lastCommit": "2026-01-29T07:51:38Z",
    "nameWithOwner": "menisadi/numrow.nvim",
    "primaryLanguage": {
      "color": "#000080",
      "name": "Lua"
    },
    "star": 1,
    "topics": [
    ]
  },
  "domain": "github.com",
  "name": "numrow.nvim",
  "owner": "menisadi",
  "url": "https://github.com/menisadi/numrow.nvim"
}